by/__init__.py
by/pressure.py
by/unconditional_situations.py
by/common/__init__.py
by/common/constants.py
by/common/sql.py
by/common/utilities.py
common/__init__.py
common/constants.py
common/sql.py
common/utilities.py
rr/__init__.py
rr/by/__init__.py
rr/by/pressure.py
rr/by/unconditional_situations.py
rr/by/common/__init__.py
rr/by/common/constants.py
rr/by/common/sql.py
rr/by/common/utilities.py
rr/common/__init__.py
rr/common/constants.py
rr/common/sql.py
rr/common/utilities.py
rr_psychology/__init__.py
rr_psychology/by/__init__.py
rr_psychology/by/pressure.py
rr_psychology/by/unconditional_situations.py
rr_psychology/by/common/__init__.py
rr_psychology/by/common/constants.py
rr_psychology/by/common/sql.py
rr_psychology/by/common/utilities.py
rr_psychology-2.3.dist-info/LICENSE
rr_psychology-2.3.dist-info/METADATA
rr_psychology-2.3.dist-info/WHEEL
rr_psychology-2.3.dist-info/top_level.txt
rr_psychology-2.3.dist-info/RECORD
